{
  "w_goal": 150.0,
  "n_soc": 2.0,
  "b_l": 1.0,
  "r_coeff": 100.0,
  "v_ref": 10.0,
  "path_tube_width": 1.5,
  "conflict_s_margin": 4.0,
  "sigma_l": 0.6,
  "tau_safe": 0.3,
  "beta_time": 0.8,
  "lambda_path_conflict": 8.0,
  "w_overlap": 1.0,
  "ped_bike_weight": 3.0,
  "vehicle_weight": 1.0,
  "crossing_speed_scale": 0.5,
  "sigma_s": 4.0,
  "selection_metric": "val_mean_objective",
  "selection_value": 3.513979204261152,
  "cap_step": 0,
  "workers": 24,
  "random_trials": 128,
  "terminal_samples": 50,
  "seed": 2025,
  "expert_mode": "local_horizon",
  "social_config": {
    "filter_mode": "union",
    "coupling": "ego_speed",
    "k": 1.0,
    "T0": 2.0,
    "r_safe": 1.0,
    "front_weight": 1.0,
    "back_weight": 0.5,
    "lateral_weight": 1.0,
    "v_floor_s": 0.5,
    "v_floor_l": 0.2,
    "slack_back": 10.0,
    "front_s_window": 50.0,
    "back_s_window": 12.0,
    "lat_window": 8.0,
    "goal_s_window": 28.0,
    "goal_l_window": 12.0,
    "path_conflict_enabled": true,
    "path_tube_width": 1.5,
    "conflict_s_margin": 4.0,
    "sigma_l": 0.6,
    "tau_safe": 0.3,
    "beta_time": 0.8,
    "lambda_path_conflict": 8.0,
    "w_overlap": 1.0,
    "ped_bike_weight": 3.0,
    "vehicle_weight": 1.0,
    "crossing_speed_scale": 0.5,
    "sigma_s": 4.0,
    "path_conflict_mode": "per_step",
    "action_field_component_scaled": true,
    "action_field_alpha": 1.0,
    "action_field_scale_physical": 16373.997814288825,
    "action_field_scale_pc": 0.2780165608838921,
    "action_field_clip": 5.0
  },
  "method": "dynamic_full_horizon_component_scaled_v5_small_gate_alpha1",
  "component_scales_source": "LeastAction/Review2/action_field_component_scaling_v5/results_dynamic_full_horizon_component_scaled_v5/component_scales.json"
}
